<?xml version="1.0" encoding="utf-8" standalone="yes"?>
<Dictionary Label="TURNING" Datatype="Dictionary">
  <Data Number="0" Location="0.97186046113826308" Referencing="0.78096774806249247" />
  <Data Number="1" Location="0.30483917498160923" Referencing="0.70280917456154357" />
  <Data Number="2" Location="-0.44004459918645766" Referencing="0.77041050255342169" />
  <Data Number="3" Location="-0.6403575187922419" Referencing="0.94499302045702316" />
  <Data Number="4" Location="-0.70656013160482511" Referencing="0.7684717734211266" />
  <Data Number="5" Location="-0.866279981464816" Referencing="0.76720533404280933" />
  <Data Number="6" Location="-0.52119114286620216" Referencing="0.72350109159064158" />
  <Data Number="7" Location="0.57330518530775731" Referencing="0.783898108908134" />
  <Data Number="8" Location="-0.19828248778707586" Referencing="0.81543184956249559" />
  <Data Number="9" Location="-0.82984458096756064" Referencing="0.82206232568499871" />
  <Data Number="10" Location="-0.7756002155107744" Referencing="0.76853020796476934" />
  <Data Number="11" Location="0.03116969008889222" Referencing="0.66112718624295785" />
  <Data Number="12" Location="0.68332191788114827" Referencing="0.869257157327669" />
  <Data Number="13" Location="-0.4987769474286331" Referencing="0.74248296017780213" />
  <Data Number="14" Location="-0.80673945029736649" Referencing="0.7944141117860879" />
  <Data Number="15" Location="0.43522700548137633" Referencing="0.82762108457021477" />
  <Data Number="16" Location="-0.013161772430422514" Referencing="0.68996770640823923" />
  <Data Number="17" Location="-0.24171209885143324" Referencing="0.76090151318132371" />
  <Data Number="18" Location="-0.57078326015140968" Referencing="0.87381078625086761" />
  <Data Number="19" Location="0.87226714492417257" Referencing="0.70468457032755183" />
</Dictionary>