<?xml version="1.0" encoding="utf-8" standalone="yes"?>
<Dictionary Label="TABLETOP" Datatype="Dictionary">
  <Data Number="0" Location="-0.59552985713256668" />
  <Data Number="1" Location="-0.75593400804715571" />
  <Data Number="2" Location="0.84960448758544926" />
  <Data Number="3" Location="0.62546488509188947" />
  <Data Number="4" Location="0.88794574439316643" />
  <Data Number="5" Location="-0.12823355645903861" />
  <Data Number="6" Location="0.21095306180348453" />
  <Data Number="7" Location="-0.5902893017431361" />
  <Data Number="8" Location="-0.17164892268557361" />
  <Data Number="9" Location="-0.51577475667382033" />
  <Data Number="10" Location="0.26040393010152685" />
  <Data Number="11" Location="0.97824845299395513" />
  <Data Number="12" Location="-0.23149254393015487" />
  <Data Number="13" Location="-0.15993720556254212" />
  <Data Number="14" Location="-0.428103485107675" />
  <Data Number="15" Location="0.93149349486411559" />
  <Data Number="16" Location="-0.13526783586838492" />
  <Data Number="17" Location="0.971725981905727" />
  <Data Number="18" Location="-0.3446126169697627" />
  <Data Number="19" Location="-0.0056182562830186279" />
</Dictionary>