<?xml version="1.0" encoding="utf-8" standalone="yes"?>
<Dictionary Label="WALK" Datatype="Dictionary">
  <Data Number="0" Referencing="0" Location="-0.57126049652960964" />
  <Data Number="1" Referencing="1" Location="0.49735665661017481" />
  <Data Number="2" Referencing="2" Location="-0.00690033772422379" />
  <Data Number="3" Referencing="3" Location="-0.38736950772915552" />
  <Data Number="4" Referencing="4" Location="-0.93158885874938857" />
  <Data Number="5" Referencing="5" Location="0.45776668612450222" />
  <Data Number="6" Referencing="6" Location="-1" />
  <Data Number="7" Referencing="7" Location="0.28463216278917725" />
</Dictionary>