<?xml version="1.0" encoding="utf-8" standalone="yes"?>
<Dictionary Label="PASSAGE" Datatype="Dictionary">
  <Data Number="0" Referencing="0" Location="-0.59835804758300215" />
  <Data Number="1" Referencing="1" Location="-0.86352266860487625" />
  <Data Number="2" Referencing="2" Location="0.19995984178635257" />
  <Data Number="3" Referencing="3" Location="0.519637849889527" />
  <Data Number="4" Referencing="4" Location="-0.024483052598458621" />
  <Data Number="5" Referencing="5" Location="0.2951081551130828" />
  <Data Number="6" Referencing="6" Location="-0.00481047812342994" />
  <Data Number="7" Referencing="7" Location="-0.195388151889382" />
</Dictionary>