<?xml version="1.0" encoding="utf-8" standalone="yes"?>
<Dictionary Label="OHDOOR" Datatype="Dictionary">
  <Data Number="0" Location="0.41732543288479446" />
  <Data Number="1" Location="0.33050862416988269" />
  <Data Number="2" Location="0.27620590286026614" />
  <Data Number="3" Location="0.59944724906086622" />
  <Data Number="4" Location="0.34311974464934869" />
  <Data Number="5" Location="0.22316833809972064" />
  <Data Number="6" Location="0.66938809178151859" />
  <Data Number="7" Location="0.074770602583897935" />
  <Data Number="8" Location="-0.057598787574230849" />
  <Data Number="9" Location="-0.5416746828445832" />
  <Data Number="10" Location="-0.42827975742099234" />
  <Data Number="11" Location="0.19677229309179434" />
  <Data Number="12" Location="-0.23188843607649626" />
  <Data Number="13" Location="0.10349817560092427" />
  <Data Number="14" Location="-0.26205504483764391" />
  <Data Number="15" Location="-0.732542326736821" />
  <Data Number="16" Location="0.65641765447974387" />
  <Data Number="17" Location="-0.13321004367242137" />
  <Data Number="18" Location="-0.96521368546777753" />
  <Data Number="19" Location="-0.39385391343224879" />
</Dictionary>