<?xml version="1.0" encoding="utf-8" standalone="yes"?>
<Dictionary Label="PENDANT" Datatype="Dictionary">
  <Data Number="0" Location="-0.76564344245502969" Referencing="0.78024473756563439" />
  <Data Number="1" Location="0.8314330211373655" Referencing="0.69242462405946636" />
  <Data Number="2" Location="-0.35695445661887804" Referencing="0.7012778392934822" />
  <Data Number="3" Location="-0.90957936245971527" Referencing="0.84923015868859786" />
  <Data Number="4" Location="-0.47956868177492185" Referencing="0.59807471806939061" />
  <Data Number="5" Location="0.13722096990791341" Referencing="0.81046571724226457" />
  <Data Number="6" Location="0.8007359416245019" Referencing="0.75689810092541443" />
  <Data Number="7" Location="0.28225736056430628" Referencing="0.63681984391728175" />
  <Data Number="8" Location="-0.43373629301596295" Referencing="0.7062034333895687" />
  <Data Number="9" Location="0.74625074460253982" Referencing="0.63703257690671611" />
  <Data Number="10" Location="-0.73940849616937454" Referencing="0.65916119855712452" />
  <Data Number="11" Location="-0.64114720218263743" Referencing="0.64818081712264142" />
  <Data Number="12" Location="-0.11133129745465138" Referencing="0.81132309412789294" />
  <Data Number="13" Location="0.88858698803013514" Referencing="0.78680249393242152" />
  <Data Number="14" Location="0.0056152003001519188" Referencing="0.731569142688244" />
  <Data Number="15" Location="0.58224778742698957" Referencing="0.61031206730343324" />
  <Data Number="16" Location="0.068218998160317026" Referencing="0.64954090379229223" />
  <Data Number="17" Location="0.1147736438999693" Referencing="0.58457310638474846" />
  <Data Number="18" Location="-0.7585442665449883" Referencing="0.79370950276499641" />
  <Data Number="19" Location="0.1532026450966702" Referencing="0.54474696591279625" />
</Dictionary>